{"cameraMode":{"drawMode":0,"name":"Shaded","section":"Shading Mode"},"sceneLighting":true,"audioPlay":false,"sceneViewState":{"m_AlwaysRefresh":false,"showFog":true,"showSkybox":true,"showFlares":true,"showImageEffects":true,"showParticleSystems":true,"showVisualEffectGraphs":true,"m_FxEnabled":true},"in2DMode":false,"pivot":{"x":6.70285177230835,"y":8.11813735961914,"z":77.0012435913086},"rotation":{"x":-0.02737143076956272,"y":-0.8258906006813049,"z":0.04039378836750984,"w":-0.5618771910667419},"size":1.4421638250350953,"orthographic":false}