{"cameraMode":{"drawMode":0,"name":"Shaded","section":"Shading Mode"},"sceneLighting":true,"audioPlay":false,"sceneViewState":{"m_AlwaysRefresh":false,"showFog":false,"showSkybox":true,"showFlares":true,"showImageEffects":true,"showParticleSystems":true,"showVisualEffectGraphs":true,"m_FxEnabled":true},"in2DMode":false,"pivot":{"x":20.421510696411134,"y":2.040128707885742,"z":29.800704956054689},"rotation":{"x":-0.16953085362911225,"y":-0.20761464536190034,"z":0.036560311913490298,"w":-0.9627143740653992},"size":10.0,"orthographic":false}